README.md
setup.py
xapi/__init__.py
xapi/apps.py
xapi/docs.py
xapi/models.py
xapi/sites.py
xapi/test.py
xapi/urls.py
xapi/util.py
xapi.egg-info/PKG-INFO
xapi.egg-info/SOURCES.txt
xapi.egg-info/dependency_links.txt
xapi.egg-info/not-zip-safe
xapi.egg-info/requires.txt
xapi.egg-info/top_level.txt
xapi/views/__init__.py
xapi/views/base.py
xapi/views/delete.py
xapi/views/detail.py
xapi/views/edit.py
xapi/views/list.py