Metadata-Version: 1.0
Name: xapi
Version: 0.0.3
Summary: django-xapi
Home-page: https://github.com/atuple/xapi
Author: sai
Author-email: 3030159@qq.com
License: MIT
Keywords: django,rest,api
Platform: UNKNOWN
